README.md
setup.py
pyfurby/__init__.py
pyfurby/background.py
pyfurby/buttons.py
pyfurby/compound_moves.py
pyfurby/gyro.py
pyfurby/motor.py
pyfurby/restless.py
pyfurby/sound.py
pyfurby/talk.py
pyfurby/temporary.py
pyfurby/tests.py
pyfurby/told.py
pyfurby.egg-info/PKG-INFO
pyfurby.egg-info/SOURCES.txt
pyfurby.egg-info/dependency_links.txt
pyfurby.egg-info/requires.txt
pyfurby.egg-info/top_level.txt