Metadata-Version: 1.0
Name: pyfurby
Version: 0.1
Summary: Controlling the various parts of the Furby with Python and a Pi Zero
Home-page: https://github.com/matteoferla/pyfurby
Author: matteoferla
Author-email: matteo.ferla@gmail.com
License: MIT
Platform: UNKNOWN
